pymon/__init__.py
pymon/logger.py
pymon/main.py
pymon/monitor.py
py_mon-2.0.3.dist-info/LICENSE
py_mon-2.0.3.dist-info/METADATA
py_mon-2.0.3.dist-info/WHEEL
py_mon-2.0.3.dist-info/entry_points.txt
py_mon-2.0.3.dist-info/top_level.txt
py_mon-2.0.3.dist-info/RECORD
