Metadata-Version: 2.1
Name: py-mon
Version: 2.0.3
Summary: 🔁 Automatically restart application when file changes are detected; made for development
Home-page: https://github.com/kevinjosethomas/py-mon
Author: kevinjosethomas
Author-email: kevin.jt2007@gmail.com
Keywords: development,testing,monitor
Classifier: Programming Language :: Python :: 3
Classifier: License :: OSI Approved :: MIT License
Classifier: Operating System :: OS Independent
Requires-Python: >=3.6
License-File: LICENSE
Requires-Dist: colorama
Requires-Dist: watchdog
